<?xml version="1.0" encoding="UTF-8"?>
<!DOCTYPE configuration PUBLIC "-//mybatis.org//DTD Config 3.0//EN"
        "http://mybatis.org/dtd/mybatis-3-config.dtd">

<configuration>

  <typeAliases>
    <!--user-->
    <typeAlias type="com.example.realfisher.domain.user.DTO.AgentDTO" alias="agentdto"/>
    <typeAlias type="com.example.realfisher.domain.user.DTO.LesseeDTO" alias="lesseedto"/>
    <typeAlias type="com.example.realfisher.domain.user.DTO.LessorDTO" alias="lessordto"/>
    <typeAlias type="com.example.realfisher.domain.user.DTO.UserDTO" alias="userdto"/>

    <!--transaction-->
    <typeAlias type="com.example.realfisher.domain.transaction.DTO.TotalTransactionDTO" alias="totaltransactiondto"/>
    <typeAlias type="com.example.realfisher.domain.transaction.DTO.UserAccountDTO" alias="useraccountdto"/>

    <!--serach-->
    <typeAlias type="com.example.realfisher.domain.search.DTO.RealEstateOfficeDTO" alias="realestateofficedto"/>
    <typeAlias type="com.example.realfisher.domain.search.DTO.ReviewDTO" alias="reviewdto"/>

    <!--contract-->
    <typeAlias type="com.example.realfisher.domain.contract.DTO.BuildingDTO" alias="buildingdto"/>
    <typeAlias type="com.example.realfisher.domain.contract.DTO.ContractDTO" alias="contractdto"/>
  </typeAliases>

</configuration>